{
  "tweet_url": "https://twitter.com/AdamMumthaz/status/1545716580830482432",
  "id": 1545716580830482432,
  "user": "AdamMumthaz",
  "time_create_ut": 1657362525,
  "text": "#Live update: Former Army Commander Sarath Fonseka arrives in Fort #GotabayaRajapaksa #SriLanka #SriLankaProtests #SriLankaCrisis #SrilankaNews #lka #SriLankaEconomicCrisis #SriLankanpoliticalcrisis #\u0d85\u0dbb\u0d9c\u0dbd\u0dba\u0da7\u0da2\u0dba #GoHomeGota #GoHomeGota2022 #July9th https://t.co/aRdZvAkLxh",
  "photo_url_list": [
    "https://pbs.twimg.com/media/FXN0y6FaQAAFjpN.jpg"
  ],
  "video_url_list": [],
  "photo_file_name": "twtr_data/1545716580830482432.photo.00.jpg"
}