{
  "tweet_url": "https://twitter.com/ShamsherSLive/status/1545727860580634630",
  "id": 1545727860580634630,
  "user": "ShamsherSLive",
  "time_create_ut": 1657365214,
  "text": "Protesters in the #SriLanka Presidential Kitchen. #GoHomeGota \u0916\u093e\u0928\u0947 \u0915\u093e \u0938\u094d\u0935\u093e\u0926 \u0909\u0920\u093e\u0924\u0940 \u0906\u092e \u091c\u0928\u0924\u093e #SriLankaCrisis https://t.co/t8gbztRHoQ",
  "photo_url_list": [],
  "video_url_list": [
    "https://video.twimg.com/ext_tw_video/1545727819677716480/pu/vid/490x270/p8YvoO4R-NT5xG01.mp4"
  ],
  "video_file_name": "twtr_data/1545727860580634630.video.00.mp4",
  "video_clip_file_list": [
    "twtr_data/1545727860580634630.video.00.mp4.clip.00.png",
    "twtr_data/1545727860580634630.video.00.mp4.clip.01.png",
    "twtr_data/1545727860580634630.video.00.mp4.clip.02.png"
  ]
}