{
  "tweet_url": "https://twitter.com/gctamil_news/status/1545374570672435200",
  "id": 1545374570672435200,
  "user": "gctamil_news",
  "time_create_ut": 1657280983,
  "text": "#GoHomeGota #GoHomeRajapaksas #gotabaya #gohomegota2022 #SriLankaEconomicCrisis #srilanka #jaffna #lanka #ceylon #jaffna #eelam #eelamtamil #tamil #TamilNews #tamilpolitics #mkstakin #dmk #ntk #seeman #tnpsc #tamilnadu\n\nhttps://t.co/VRwoMgyU41 https://t.co/v9Sk3bqHU8",
  "photo_url_list": [],
  "video_url_list": [
    "https://video.twimg.com/ext_tw_video/1545374480251650048/pu/vid/720x720/JyEa-OhKlFAqZwqC.mp4"
  ],
  "video_file_name": "twtr_data/1545374570672435200.video.00.mp4",
  "video_clip_file_list": [
    "twtr_data/1545374570672435200.video.00.mp4.clip.00.png"
  ]
}