{
  "tweet_url": "https://twitter.com/Dewmina_Uday/status/1545577026450767872",
  "id": 1545577026450767872,
  "user": "Dewmina_Uday",
  "time_create_ut": 1657329253,
  "text": "Today is our day. Let's show these corrupt politicians our unity. Let's win together, let's protect our motherland \u2764\ufe0f\n#GoHomeGota2022 #GoHomeGota #SriLankaEconomicCrisis https://t.co/PaAIq8oTSc",
  "photo_url_list": [
    "https://pbs.twimg.com/media/FXL-HV2aUAAJdAc.jpg"
  ],
  "video_url_list": [],
  "photo_file_name": "twtr_data/1545577026450767872.photo.00.jpg"
}