{
  "tweet_url": "https://twitter.com/soysa007/status/1545440514433884161",
  "id": 1545440514433884161,
  "user": "soysa007",
  "time_create_ut": 1657296706,
  "text": "True \ud83e\udd23 , Internet \u0d92\u0d9a\u0dad\u0dca Down \u0d9a\u0dbb\u0db1\u0dca\u0db1, \u0dc3\u0dca\u0dad\u0dd6\u0dad\u0dd2\u0dba\u0dd2!\n\n#LKA #SriLanka #SriLankaCrisis #SriLankaEconomicCrisis #EconomicCrisisLK \n#ProtestLK #LKProtest #GoHomeRajapakshas #GoHomeGota #GoHomeGota2022 #GoHomeRanil https://t.co/KltR1v3JqC",
  "photo_url_list": [
    "https://pbs.twimg.com/media/FXKB9R5UsAAZzJ9.jpg"
  ],
  "video_url_list": [],
  "photo_file_name": "twtr_data/1545440514433884161.photo.00.jpg"
}