{
  "tweet_url": "https://twitter.com/WedabimaL/status/1545259014224809990",
  "id": 1545259014224809990,
  "user": "WedabimaL",
  "time_create_ut": 1657253433,
  "text": "In #protest against the current #government, several monk organizations are starting a #Satyagraha in pettah..\n#GoHomeGota #EconomicCrisisLK #GoHomeRajapaksas #FuelCrisisLK #SriLanka #SriLankaEconomicCrisis #SriLankaProtests https://t.co/Nltp9PCmc2",
  "photo_url_list": [
    "https://pbs.twimg.com/media/FXHciBHX0AA-SNF.jpg",
    "https://pbs.twimg.com/media/FXHciBdWYAEuLIh.jpg",
    "https://pbs.twimg.com/media/FXHciBvWQAELB3u.jpg",
    "https://pbs.twimg.com/media/FXHciCEXEAAPbWG.jpg"
  ],
  "video_url_list": []
}