{
  "tweet_url": "https://twitter.com/FraudTwitz2/status/1545450168648347648",
  "id": 1545450168648347648,
  "user": "FraudTwitz2",
  "time_create_ut": 1657299007,
  "text": "\u0b86\u0bb0\u0bae\u0bcd\u0baa\u0bbf\u0b95\u0bcd\u0b95\u0bb2\u0bbe\u0bae\u0bbe..?\n\n\u0b9c\u0ba9\u0bbe\u0ba4\u0bbf\u0baa\u0ba4\u0bbf \u0bae\u0bbe\u0bb3\u0bbf\u0b95\u0bc8\u0baf\u0bbf\u0ba9\u0bcd \u0bae\u0bc1\u0ba9\u0bcd \u0ba4\u0bbf\u0bb0\u0ba3\u0bcd\u0b9f \u0bae\u0b95\u0bcd\u0b95\u0bb3\u0bcd..\n\n#gohomegota2022 #SriLanka #GoHomeGota https://t.co/PhEnvFtneg",
  "photo_url_list": [
    "https://pbs.twimg.com/media/FXKKu_caMAEJBOW.jpg"
  ],
  "video_url_list": [],
  "photo_file_name": "twtr_data/1545450168648347648.photo.00.jpg"
}