{
  "tweet_url": "https://twitter.com/pdpcric__/status/1545639369218101248",
  "id": 1545639369218101248,
  "user": "pdpcric__",
  "time_create_ut": 1657344116,
  "text": "Power of People #GoHomeGota #GoHomeGota2022 https://t.co/68m89RYhWc",
  "photo_url_list": [
    "https://pbs.twimg.com/media/FXM2vs8aAAAWKrG.jpg",
    "https://pbs.twimg.com/media/FXM2wQ5aAAAoxBd.jpg",
    "https://pbs.twimg.com/media/FXM20IhaQAElZ-0.jpg"
  ],
  "video_url_list": [],
  "photo_file_name": "twtr_data/1545639369218101248.photo.02.jpg"
}