{
  "tweet_url": "https://twitter.com/mdlucias/status/1545637843090886657",
  "id": 1545637843090886657,
  "user": "mdlucias",
  "time_create_ut": 1657343753,
  "text": "Tear gas fired on protesters near the Lake House Colombo\n\n#Srilanka #GoHomeGota #Colombo #\u0d85\u0dbb\u0d9c\u0dbd\u0dba\u0da7\u0da2\u0dba #GoHomeRanil #lka https://t.co/ewBLViyjIW",
  "photo_url_list": [],
  "video_url_list": [
    "https://video.twimg.com/ext_tw_video/1545637779765428224/pu/vid/480x270/mxJk5-NLc2y9L6Zs.mp4"
  ],
  "video_file_name": "twtr_data/1545637843090886657.video.00.mp4"
}