{
  "tweet_url": "https://twitter.com/ManujaLiyanage/status/1545721504616263680",
  "id": 1545721504616263680,
  "user": "ManujaLiyanage",
  "time_create_ut": 1657363699,
  "text": "Former President of Sri Lanka \u0dc1\u0dca\u200d\u0dbb\u0dd3 \u0dbd\u0d82\u0d9a\u0dcf\u0dc0\u0dda \u0dc4\u0dd2\u0da7\u0db4\u0dd4 \u0da2\u0db1\u0dcf\u0db0\u0dd2\u0db4\u0dad\u0dd2 @GotabayaR \n#GoHomeGota #GoHomeGota2022 https://t.co/r4iDxdZYEW",
  "photo_url_list": [
    "https://pbs.twimg.com/media/FXOBg6SVEAAC3l0.jpg"
  ],
  "video_url_list": [],
  "photo_file_name": "twtr_data/1545721504616263680.photo.00.jpg"
}