{
  "tweet_url": "https://twitter.com/mrmolombo/status/1546782449610670080",
  "id": 1546782449610670080,
  "user": "mrmolombo",
  "time_create_ut": 1657616648,
  "text": "Since IT was kicked outta ITs position and IT is officially resigning tomorrow here\u2019s a video I put together \ud83d\ude0f\ud83e\udd21 #GoHomeGota #GotabayaRajapaksa #BasilRajapaksa #kaputas #lka #aragalayatajaya #GotaGoHome2022 #SriLanka #SriLankanpoliticalcrisis https://t.co/xENgXcCHUg",
  "photo_url_list": [],
  "video_url_list": [
    "https://video.twimg.com/ext_tw_video/1546782338990112768/pu/vid/480x852/WnD3gD0TWquKbyaB.mp4"
  ],
  "video_file_name": "twtr_data/1546782449610670080.video.00.mp4",
  "video_clip_file_list": [
    "twtr_data/1546782449610670080.video.00.mp4.clip.00.png"
  ]
}