{
  "tweet_url": "https://twitter.com/Rizwanhameed27/status/1546772423718100992",
  "id": 1546772423718100992,
  "user": "Rizwanhameed27",
  "time_create_ut": 1657614258,
  "text": "I foresee a deadlock here.....\n\n#lka #SriLanka #GoHomeGota #GoHomeRanil #ProtestLK #SriLankaProtests #\u0d85\u0dbb\u0d9c\u0dbd\u0dba\u0da7\u0da2\u0dba https://t.co/JBLMRKtTkk https://t.co/QC2FaVjxJU",
  "photo_url_list": [
    "https://pbs.twimg.com/media/FXc9Ta-WIAIP_6N.png"
  ],
  "video_url_list": [],
  "photo_file_name": "twtr_data/1546772423718100992.photo.00.png"
}