{
  "tweet_url": "https://twitter.com/ShafarSham/status/1546741115616911361",
  "id": 1546741115616911361,
  "user": "ShafarSham",
  "time_create_ut": 1657606793,
  "text": "1/ \ud83e\uddf5\nSalute \ud83e\udee1 to all the officers of the immigration officers. Now these #Rajapaksa thieves will somehow try to get the flight using all their powers. #Pilots of any airline pls don\u2019t take off. They will still leave the country be sea to the nearest land\u2026 \n#GoHomeGota  #lka https://t.co/N91zcmu2rS",
  "photo_url_list": [
    "https://pbs.twimg.com/media/FXccdsUWQAIA3Nz.jpg"
  ],
  "video_url_list": [],
  "photo_file_name": "twtr_data/1546741115616911361.photo.00.jpg"
}