{
  "tweet_url": "https://twitter.com/lukshayanmuthu/status/1546668325375057921",
  "id": 1546668325375057921,
  "user": "lukshayanmuthu",
  "time_create_ut": 1657589439,
  "text": "Whole family running away from SriLanka in MK 9935 to Dubai ?. #GoHomeGota #GoHomeRanil #srilanka #EconomicCrisisLK @munza14 @rangaba https://t.co/ykabL84Cm2",
  "photo_url_list": [
    "https://pbs.twimg.com/media/FXbeoNiUIAA3MSK.jpg"
  ],
  "video_url_list": [],
  "photo_file_name": "twtr_data/1546668325375057921.photo.00.jpg"
}