{
  "tweet_url": "https://twitter.com/I_am_Thomi/status/1546513816028069889",
  "id": 1546513816028069889,
  "user": "I_am_Thomi",
  "time_create_ut": 1657552601,
  "text": "\"\u0d94\u0db6 \u0dc0\u0dd2\u0dc3\u0dd2\u0db1\u0dca \u0db8 \u0db1\u0dd2\u0db8\u0dcf \u0d9a\u0dbb\u0db4\u0dd4 \u0daf\u0dc1\u0d9a \u0d9c\u0dcf\u0db1\u0d9a \u0dc4\u0dc0\u0dd4\u0dbd\"\n\n\"\u0da2\u0dba \u0dc3\u0db8\u0dbb\u0db1\u0dca\u0db1 - 13 \u0d9a\u0ddc\u0dc5\u0db9 \u0d91\u0db1\u0dca\u0db1\"\n\nCopied \n#GoHomeGota https://t.co/2KCOS50RWv",
  "photo_url_list": [
    "https://pbs.twimg.com/media/FXZSHiRWYAEr6IO.jpg"
  ],
  "video_url_list": [],
  "photo_file_name": "twtr_data/1546513816028069889.photo.00.jpg"
}