{
  "tweet_url": "https://twitter.com/kavinuishere/status/1547068945278021633",
  "id": 1547068945278021633,
  "user": "kavinuishere",
  "time_create_ut": 1657684954,
  "text": "Hello @netflix, something to consider !!! \ud83d\ude05\u2764\n\"Man who ran for president now running from presidency...\"\n\n#GOHOMEGOTA https://t.co/iDUqvogfLV",
  "photo_url_list": [
    "https://pbs.twimg.com/media/FXhLACZUsAIZELZ.jpg"
  ],
  "video_url_list": [],
  "photo_file_name": "twtr_data/1547068945278021633.photo.00.jpg"
}