{
  "tweet_url": "https://twitter.com/bestbuyers7/status/1547100193312628742",
  "id": 1547100193312628742,
  "user": "bestbuyers7",
  "time_create_ut": 1657692404,
  "text": "Sri Lanka President Gotabaya Rajapaksa flees to Maldives as protests escalate | Top Points   https://t.co/xFLdtwz6U0 #news  #worldnews #srilanka #maldivestiktok #colombo #srilankanews #protest #viral #viralvideo #fyp #foryou #gohomegota #gohomeranil https://t.co/vzjzpicwhv",
  "photo_url_list": [],
  "video_url_list": [
    "https://video.twimg.com/ext_tw_video/1547099935706959877/pu/vid/748x306/toEwBMzmj0j-HDIx.mp4"
  ],
  "video_file_name": "twtr_data/1547100193312628742.video.00.mp4"
}