{
  "tweet_url": "https://twitter.com/tamil_butterfly/status/1547130093851770881",
  "id": 1547130093851770881,
  "user": "tamil_butterfly",
  "time_create_ut": 1657699533,
  "text": "\ud83d\udd34 Breaking news \ud83d\udd34 \u0da2\u0dcf\u0dad\u0dd2\u0d9a \u0dbb\u0dd6\u0db4\u0dc0\u0dcf\u0dc4\u0dd2\u0db1\u0dd3 \u0db1\u0dcf\u0dbd\u0dd2\u0d9a\u0dcf\u0dc0 \u0d85\u0dbb\u0d9c\u0dbd\u0d9a\u0dbb\u0dd4\u0dc0\u0db1\u0dca \u0d85\u0dad\u0dca\u0db4\u0dad\u0dca \u0d9a\u0dbb\u0d9c\u0dd9\u0db1 \u0dad\u0dd2\u0db6\u0dd9\u0db1\u0dc0\u0dcf.. \n\n#GoHomeGota #colombo\u00a0 #lka #GoHomeRanil #\u0d85\u0dbb\u0d9c\u0dbd\u0dba\u0da7\u0da2\u0dba #BRAKINGNEWS #SriLankaCrisis #SriLankaProtests #SriLankaEconomicCrisis #SriLankaToday #SrilankaNews #news #LocalNews #Trending\u00a0\u00a0 #LatestNews\u00a0 #lka https://t.co/8QEqWHAhPv",
  "photo_url_list": [
    "https://pbs.twimg.com/media/FXiCnSpacAApYvW.jpg"
  ],
  "video_url_list": [],
  "photo_file_name": "twtr_data/1547130093851770881.photo.00.jpg"
}