{
  "tweet_url": "https://twitter.com/hgwelgama/status/1547148868533436416",
  "id": 1547148868533436416,
  "user": "hgwelgama",
  "time_create_ut": 1657704009,
  "text": "A kindly reminder fo all the People who are in the frontlines of the struggle, Please make yourselves new as we drive towards a new way! Keep the public properties as they are!\ud83d\ude4f\ud83c\udffb They are our money!\n\n#GoHomeRanil #aragalayatajaya #GoHomeGota https://t.co/tdNHJ4p5Eq",
  "photo_url_list": [
    "https://pbs.twimg.com/media/FXiTp_gUEAAM0Ee.jpg"
  ],
  "video_url_list": [],
  "photo_file_name": "twtr_data/1547148868533436416.photo.00.jpg"
}