{
  "tweet_url": "https://twitter.com/Shaanttey/status/1547064783979282432",
  "id": 1547064783979282432,
  "user": "Shaanttey",
  "time_create_ut": 1657683962,
  "text": "\u078d\u07a6\u0782\u07b0\u0786\u07a7\u078e\u07ac \u0789\u07a6\u079d\u07b0\u0780\u07ab\u0783\u07aa \u0782\u07ab\u0790\u07b0\u0788\u07ac\u0783\u07a8\u0787\u07ac\u0787\u07b0 \u0786\u07a6\u0789\u07a6\u0781\u07b0\u0788\u07a7 \u079d\u07a8\u0780\u07a7\u0783\u07aa \u0787\u07a6\u0782\u07a9\u0790\u07b0\u078e\u07ac \u0793\u07b0\u0788\u07a9\u0793\u07ac\u0787\u07b0.\n@shiharaneez #SriLanka #SriLankaProtests #SendGotaBackToHome #GoHomeGota https://t.co/PTO34j91py",
  "photo_url_list": [
    "https://pbs.twimg.com/media/FXhHN4SacAE5R_F.jpg"
  ],
  "video_url_list": [],
  "photo_file_name": "twtr_data/1547064783979282432.photo.00.jpg"
}